<entry xml:id="mw-pwg-pwk-BadreSa">
  <form type="compound">
    <orth notation="SLP1">BadreSa</orth>
  </form>
  <note type="source" target="mw">&lt;L&gt;148511&lt;pc&gt;746,3&lt;k1&gt;BadreSa&lt;k2&gt;BadreSa&lt;e&gt;3 &lt;s&gt;Badre&lt;srs/&gt;Sa&lt;/s&gt; ¦ See &lt;s&gt;Badre&lt;srs/&gt;Sa&lt;/s&gt; &amp;c. &lt;hom&gt;1.&lt;/hom&gt; &lt;s&gt;BadrA&lt;/s&gt; below.&lt;info hui=&quot;a&quot;/&gt; &lt;LEND&gt;</note>
  <note type="source" target="pwg">&lt;L&gt;54093&lt;pc&gt;5-0200&lt;k1&gt;BadreSa&lt;k2&gt;BadreSa {#BadreSa#}¦ ({#Badra + ISa#}) &lt;lex&gt;m.&lt;/lex&gt; Bein. &lt;is&gt;Śiva&apos;s&lt;/is&gt; &lt;ls&gt;PAÑCAR. 1,15,25.&lt;/ls&gt; &lt;LEND&gt;</note>
  <note type="source" target="pwk">&lt;L&gt;78801&lt;pc&gt;4-250-a&lt;k1&gt;BadreSa&lt;k2&gt;BadreSa {#BadreSa#}¦ &lt;lex&gt;m.&lt;/lex&gt; &lt;ab&gt;Bein.&lt;/ab&gt; &lt;is&gt;Śiva&lt;/is&gt;ʼs. &lt;LEND&gt;</note>
  <note type="model-loss">Machine-generated stub; not reviewed.</note>
</entry>
