<entry xml:id="mw-pwg-pwk-arTAntara">
  <form type="lemma"><orth notation="SLP1">arTAntara</orth></form>
  <note type="source" target="mw">&lt;L&gt;16023&lt;pc&gt;91,2&lt;k1&gt;arTAntara&lt;k2&gt;arTAntara&lt;e&gt;3 &lt;s&gt;arTA&lt;srs/&gt;ntara&lt;/s&gt; ¦ &lt;lex&gt;n.&lt;/lex&gt; another matter, a different or new circumstance, a similar case (often with &lt;s&gt;ny-&lt;/s&gt; √ &lt;hom&gt;2.&lt;/hom&gt; &lt;s&gt;as&lt;/s&gt;, to introduce some other matter as an illustration See &lt;s&gt;arTA&lt;srs/&gt;ntara-nyAsa&lt;/s&gt; below)&lt;info lex=&quot;n&quot;/&gt; &lt;LEND&gt;</note>
  <note type="source" target="pwg">&lt;L&gt;65145&lt;pc&gt;5-1047&lt;k1&gt;arTAntara&lt;k2&gt;arTAntara {#arTAntara#}¦ &lt;div n=&quot;1&quot;&gt; 1) {%etwas Anderes%} &lt;ls&gt;SĀH. D. 460.&lt;/ls&gt; {#arTAntaraM nyas#} bedeutet in der Rhetorik {%eine Erscheinung zu einer anderen in Beziehung setzen und sie dadurch zu erklären suchen%}, z. B. {%einen einzelnen Fall durch einen allgemeinen oder umgekehrt einen allgemeinen durch einen einzelnen; einen analogen Fall beibringen.%} {#arTAntaranyAsa#} &lt;ls&gt;KĀVYĀD. 2,169.&lt;/ls&gt; &lt;ls&gt;SĀH. D. 709.&lt;/ls&gt; &lt;ls&gt;PRATĀPAR. 98,a,8.&lt;/ls&gt; &lt;ls&gt;KUVALAY. 122,b&lt;/ls&gt; (&lt;ls n=&quot;KUVALAY.&quot;&gt;147,b&lt;/ls&gt;). &lt;ls&gt;Verz. d. Oxf. H. 208,b,21.&lt;/ls&gt; &lt;ls&gt;MALLIN.&lt;/ls&gt; zu &lt;ls&gt;KIR. 5,51.&lt;/ls&gt; &lt;div n=&quot;1&quot;&gt;— 2) {#arTAntaraM saMkramite vAcye#} &lt;ls&gt;SĀH. D. 253.&lt;/ls&gt; &lt;ls n=&quot;SĀH. D.&quot;&gt;584.&lt;/ls&gt; &lt;ls&gt;Schol.&lt;/ls&gt; zu &lt;ls&gt;AV. PRĀT. 4,102.&lt;/ls&gt; &lt;LEND&gt;</note>
  <note type="source" target="pwk">&lt;L&gt;9536&lt;pc&gt;1-112-a&lt;k1&gt;arTAntara&lt;k2&gt;arTAntara {#arTAntara#}¦ &lt;lex&gt;n.&lt;/lex&gt; &lt;div n=&quot;1&quot;&gt;— 1〉 {%etwas Anderes%}. Mit &lt;ab&gt;Abl.&lt;/ab&gt; &lt;ls n=&quot;Chr.&quot;&gt;231,29&lt;/ls&gt;. &lt;ls&gt;NYĀYAS. 5,2,7&lt;/ls&gt;. &lt;div n=&quot;1&quot;&gt;— 2〉 {%eine andere Bedeutung%}. &lt;LEND&gt;</note>
  <note type="model-loss">Machine-generated stub; not reviewed.</note>
</entry>
